LICENSE
README.md
setup.py
vision_models_playground/__init__.py
vision_models_playground/metadata.py
vision_models_playground.egg-info/PKG-INFO
vision_models_playground.egg-info/SOURCES.txt
vision_models_playground.egg-info/dependency_links.txt
vision_models_playground.egg-info/requires.txt
vision_models_playground.egg-info/top_level.txt
vision_models_playground/components/__init__.py
vision_models_playground/components/activations/__init__.py
vision_models_playground/components/activations/geglu.py
vision_models_playground/components/activations/gelu.py
vision_models_playground/components/activations/hard_sigmoid.py
vision_models_playground/components/activations/mish.py
vision_models_playground/components/activations/quick_geglu.py
vision_models_playground/components/activations/quick_gelu.py
vision_models_playground/components/activations/relu_squared.py
vision_models_playground/components/activations/swish.py
vision_models_playground/components/attention/__init__.py
vision_models_playground/components/attention/attend.py
vision_models_playground/components/attention/attention.py
vision_models_playground/components/attention/compressor.py
vision_models_playground/components/attention/feed_forward.py
vision_models_playground/components/attention/post_norm.py
vision_models_playground/components/attention/pre_norm.py
vision_models_playground/components/attention/tied_embedding.py
vision_models_playground/components/attention/transformer.py
vision_models_playground/components/attention/transformer_decoder.py
vision_models_playground/components/attention/transformer_decoder_layer.py
vision_models_playground/components/attention/transformer_encoder.py
vision_models_playground/components/attention/transformer_encoder_layer.py
vision_models_playground/components/convolutions/__init__.py
vision_models_playground/components/convolutions/bottleneck_block.py
vision_models_playground/components/convolutions/conv_attend.py
vision_models_playground/components/convolutions/conv_attention.py
vision_models_playground/components/convolutions/conv_block.py
vision_models_playground/components/convolutions/conv_embedding.py
vision_models_playground/components/convolutions/conv_projection.py
