Metadata-Version: 2.1
Name: vision-models-playground
Version: 0.2.0
Summary: Akriel's vision models playground
Home-page: https://github.com/Akrielz/vision_models_playground
Author: Alexandru Stirbu
Author-email: Stirbu.Alexandru.Net@outlook.com
License: MIT
Keywords: artificial intelligence,deep learning,transformer,attention mechanism,computer vision
Classifier: Development Status :: 4 - Beta
Classifier: Intended Audience :: Developers
Classifier: Topic :: Scientific/Engineering :: Artificial Intelligence
Classifier: License :: OSI Approved :: MIT License
Classifier: Programming Language :: Python :: 3.8
License-File: LICENSE
